MANIFEST.in
README.rst
setup.cfg
setup.py
version.py
src/cgcloud/__init__.py
src/cgcloud/mesos/__init__.py
src/cgcloud/mesos/mesos_box.py
src/cgcloud/mesos/mesos_cluster.py
src/cgcloud/mesos/test/__init__.py
src/cgcloud/mesos/test/conftest.py
src/cgcloud/mesos/test/test_mesos.py
src/cgcloud_mesos.egg-info/PKG-INFO
src/cgcloud_mesos.egg-info/SOURCES.txt
src/cgcloud_mesos.egg-info/dependency_links.txt
src/cgcloud_mesos.egg-info/namespace_packages.txt
src/cgcloud_mesos.egg-info/requires.txt
src/cgcloud_mesos.egg-info/top_level.txt