Metadata-Version: 1.0
Name: cgcloud-mesos
Version: 1.6.0
Summary: Setup and manage a Apache Mesos cluster in EC2
Home-page: https://github.com/BD2KGenomics/cgcloud
Author: Christopher Ketchum
Author-email: cketchum@ucsc.edu
License: UNKNOWN
Platform: UNKNOWN
